aiogrobid/__init__.py
aiogrobid/cli.py
aiogrobid/client.py
aiogrobid/exceptions.py
aiogrobid-0.1.12.dist-info/LICENSE
aiogrobid-0.1.12.dist-info/METADATA
aiogrobid-0.1.12.dist-info/WHEEL
aiogrobid-0.1.12.dist-info/entry_points.txt
aiogrobid-0.1.12.dist-info/top_level.txt
aiogrobid-0.1.12.dist-info/RECORD
