Metadata-Version: 2.1
Name: aiogrobid
Version: 0.1.12
Home-page: https://github.com/izihawa/aiogrobid
Author: Pasha Podolsky
License: MIT
Classifier: Topic :: Utilities
License-File: LICENSE
Requires-Dist: aiobaseclient (>=0.2.4)
Requires-Dist: fire (>=0.3.1)
Requires-Dist: izihawa-types (>=0.1.0)
Requires-Dist: lxml
